{
	"mycourse": {
		"student": "studentname",
		"learningObjective": [{
				"objective": "To learn math",
				"page": 1,
				"questions": [{
						"skill": "Add two numbers together",
						"question": "What is 25 + 4?",
						"answer": 29,
						"questionType": "multiple choice",
						"selectedAnswers": [],
						"distractor": [
							"Radiation resistance",
							"Turning tiny",
							"Radiation blast"
						],
						"hint": "Incorrect: It is more than 28 and less than 30."
					},
					{
						"skill": "Multiply two numbers together",
						"question": "What is 25 * 4?",
						"answer": 100,
						"questionType": "short answer",
						"selectedAnswers": [],
						"distractor": []
						"hint": "Incorrect: It is more than 99 and less than 101."
					}
				]
			},
			{
				"objective": "To learn history",
				"page": 2,
				"questions": [{
						"skill": "US history",
						"question": "What year did the United States declare independence from Britian?",
						"answer": 1776,
						"questionType": "multiple choice",
						"selectedAnswers": [],
						"distractor": [
							"1492",
							"1619",
							"1861"
						]
					        "hint": "Incorrect: It is was before 1800."
					},
					{
						"skill": "presidents of the US",
						"question": "What was the last name of U.S. President during the civil war?",
						"answer": "Lincoln",
						"questionType": "short answer",
						"selectedAnswers": [],
						"distractor": []
						"hint": "Incorrect: Their first name was Abe."
					}
				]
			}
		]
	}
}
